LICENSE
MANIFEST.in
README.rst
setup.py
enteritidis_subtyping/__init__.py
enteritidis_subtyping/main.py
enteritidis_subtyping/subtype.py
enteritidis_subtyping/subtype_stats.py
enteritidis_subtyping/subtyper.py
enteritidis_subtyping/utils.py
enteritidis_subtyping.egg-info/PKG-INFO
enteritidis_subtyping.egg-info/SOURCES.txt
enteritidis_subtyping.egg-info/dependency_links.txt
enteritidis_subtyping.egg-info/entry_points.txt
enteritidis_subtyping.egg-info/requires.txt
enteritidis_subtyping.egg-info/top_level.txt
enteritidis_subtyping/blast_wrapper/__init__.py
enteritidis_subtyping/blast_wrapper/const.py
enteritidis_subtyping/blast_wrapper/helpers.py
enteritidis_subtyping/data/tiles.fasta
enteritidis_subtyping/kmer_count/__init__.py